snk/__about__.py
snk/__init__.py
snk/errors.py
snk/main.py
snk/nest.py
snk/utils.py
snk-0.31.1.dist-info/METADATA
snk-0.31.1.dist-info/WHEEL
snk-0.31.1.dist-info/entry_points.txt
snk-0.31.1.dist-info/licenses/LICENSE.txt
snk-0.31.1.dist-info/RECORD
