Metadata-Version: 2.3
Name: snk
Version: 0.31.1
Project-URL: Documentation, https://github.com/wytamma/snk#readme
Project-URL: Issues, https://github.com/wytamma/snk/issues
Project-URL: Source, https://github.com/wytamma/snk
Author-email: Wytamma Wirth <wytamma.wirth@me.com>
License: MIT
Classifier: Development Status :: 4 - Beta
Classifier: Programming Language :: Python
Classifier: Programming Language :: Python :: 3.8
Classifier: Programming Language :: Python :: 3.9
Classifier: Programming Language :: Python :: 3.10
Classifier: Programming Language :: Python :: 3.11
Classifier: Programming Language :: Python :: 3.12
Classifier: Programming Language :: Python :: Implementation :: CPython
Classifier: Programming Language :: Python :: Implementation :: PyPy
Requires-Python: >=3.8
Requires-Dist: gitpython~=3.1.0
Requires-Dist: snk-cli>=0.7.1
